beocijies/__init__.py
beocijies/cli.py
beocijies/configure.py
beocijies/render.py
beocijies/version.py
beocijies-0.10.0.dist-info/licenses/LICENSE.md
beocijies-0.10.0.dist-info/METADATA
beocijies-0.10.0.dist-info/WHEEL
beocijies-0.10.0.dist-info/entry_points.txt
beocijies-0.10.0.dist-info/top_level.txt
beocijies-0.10.0.dist-info/RECORD
