Metadata-Version: 2.4
Name: beocijies
Version: 0.10.0
Summary: A site generator for small handmade sites
Author-email: bcj <bcj@beocijies.com>
Project-URL: Homepage, https://github.com/bcj/beocijies
Classifier: Development Status :: 4 - Beta
Classifier: Environment :: Console
Classifier: Intended Audience :: Developers
Classifier: Operating System :: POSIX
Classifier: Programming Language :: Python :: 3
Classifier: Programming Language :: Python :: 3.9
Classifier: Programming Language :: Python :: 3.10
Classifier: Programming Language :: Python :: 3.11
Classifier: Programming Language :: Python :: 3.12
Classifier: Programming Language :: Python :: 3.13
Classifier: Topic :: Internet
Classifier: Topic :: Internet :: WWW/HTTP
Classifier: Topic :: Internet :: WWW/HTTP :: Site Management
Classifier: Topic :: Utilities
Classifier: Typing :: Typed
Requires-Python: >=3.9
License-File: LICENSE.md
Requires-Dist: beautifulsoup4
Requires-Dist: jinja2
Requires-Dist: notify-py
Requires-Dist: requests
Dynamic: license-file
